mlstreamline/__init__.py
mlstreamline/deployment_pipeline.py
mlstreamline/helper_functions.py
mlstreamline/outlier_transformer.py
mlstreamline/transformers/__init__.py
mlstreamline/transformers/custom_model_transformer.py
mlstreamline/transformers/gaussian_mixture_transformer.py
mlstreamline/transformers/outlier_transformer.py
mlstreamline-0.0.28.dist-info/LICENSE
mlstreamline-0.0.28.dist-info/METADATA
mlstreamline-0.0.28.dist-info/WHEEL
mlstreamline-0.0.28.dist-info/top_level.txt
mlstreamline-0.0.28.dist-info/RECORD
