Metadata-Version: 2.1
Name: mlstreamline
Version: 0.0.28
Summary: streamlined wrapper classes for ml
Home-page: https://upload.pypi.org/legacy/mlstreamline
Author: Charles Crawford
Author-email: crawford.charles.g@gmail.com
License: UNKNOWN
Platform: UNKNOWN
Classifier: Programming Language :: Python :: 3
Classifier: License :: OSI Approved :: MIT License
Classifier: Operating System :: OS Independent
Requires-Python: >=3.6
License-File: LICENSE
